{
  "schema_version": "industry-incremental-onboarding-manifest/v1",
  "generated_at_utc": "2026-07-10T18:25:17+00:00",
  "pipeline": "industry_incremental_onboarding",
  "design_constraints": {
    "modular": true,
    "incremental": true,
    "manual_review_in_app": true,
    "notes": [
      "Materializa apenas FIDCs novos ou reativados da competência corrente.",
      "O checklist consolida descoberta documental, processamento por chunks e incorporação às bases estruturadas.",
      "Não cria decisões de curadoria; usa a fila única e os ledgers existentes como fonte de status."
    ]
  },
  "inputs": {
    "monthly_delta": {
      "path": "data/industry_study/industry_monthly_delta.csv.gz",
      "exists": true,
      "bytes": 368198,
      "sha256": "2d08cd95508c3ed08e591cb0b08f398b67078eb2a9f2efc438fa2ac45688ccbe"
    },
    "curation_queue": {
      "path": "data/industry_study/industry_curation_queue.csv.gz",
      "exists": true,
      "bytes": 427234,
      "sha256": "7f60476ff4bf20f2ddae200a9bba8a4a6f4a689ed4ad05476e28dd711d472bd7"
    },
    "document_chunk_plan": {
      "path": "data/industry_study/document_chunk_plan.csv",
      "exists": true,
      "bytes": 88849,
      "sha256": "ca4763be0f9b90d7bcfee84c736a20004b294ee4ad8ed9a12a93dd300276c063"
    }
  },
  "outputs": {
    "incremental_onboarding": {
      "path": "data/industry_study/industry_incremental_onboarding.csv",
      "exists": true,
      "bytes": 80945,
      "sha256": "2ee77ef2ed152522ffffedb3304ffafd113de24742fb648e4b763a597fff4340"
    },
    "manifest": {
      "path": "data/industry_study/industry_incremental_onboarding_manifest.json"
    }
  },
  "stages": [
    {
      "id": "filter_new_reactivated",
      "label": "Filtrar novos e reativados",
      "status": "ok",
      "rows": 4279,
      "rerun": "python scripts/build_fidc_industry_monthly_delta.py"
    },
    {
      "id": "join_queue_and_chunks",
      "label": "Cruzar fila única e chunks documentais",
      "status": "ok",
      "rows": 8556,
      "rerun": "python scripts/build_fidc_industry_curation_queue.py"
    },
    {
      "id": "persist_onboarding_plan",
      "label": "Persistir onboarding incremental",
      "status": "ok",
      "rows": 71,
      "rerun": "python scripts/build_fidc_industry_incremental_onboarding.py"
    }
  ],
  "quality": {
    "rows": 71,
    "funds": 71,
    "new_funds": 63,
    "reactivated_funds": 8,
    "blocked_rows": 61,
    "attention_rows": 10,
    "ok_rows": 0,
    "discovery_blocked": 2,
    "processing_attention": 69,
    "incorporation_blocked": 3,
    "open_queue_rows": 146,
    "open_high_priority_rows": 81,
    "status_counts": {
      "bloqueado": 61,
      "atenção": 10
    }
  }
}