{
  "schema_version": "industry-dimension-profile-manifest/v1",
  "generated_at_utc": "2026-07-10T01:44:58+00:00",
  "pipeline": "industry_dimension_profiles",
  "design_constraints": {
    "modular": true,
    "incremental": true,
    "macbook_air_m4_friendly": true,
    "notes": [
      "Materializa cruzamentos dimensão-origem x dimensão-alvo para Deep Dives e heatmaps.",
      "Usa apenas snapshot e catálogo já estruturados; não reprocessa informes ou documentos.",
      "Dimensões multivalor são ponderadas pelo produto dos pesos de origem e alvo."
    ]
  },
  "inputs": {
    "fund_snapshot": {
      "path": "data/industry_study/industry_fund_snapshot.csv.gz",
      "exists": true,
      "bytes": 443031,
      "sha256": "19d30da71988ef836de894da972fa978adf937c9c4a6237c4f4fb203a61cdde1"
    },
    "dimension_catalog": {
      "path": "data/industry_study/industry_dimension_catalog.csv.gz",
      "exists": true,
      "bytes": 1617284,
      "sha256": "a7ca718479ce971e85d206249c73bacf2ff939d4a0fc6166f3f2bb52e401b58e"
    }
  },
  "outputs": {
    "dimension_profiles": {
      "path": "data/industry_study/industry_dimension_profiles.csv.gz",
      "exists": true,
      "bytes": 2645995,
      "sha256": "6958f552a7c71a2fa3fcb15b438a0600635bd3de7c23b6574088dd9cd5e4c662"
    },
    "manifest": {
      "path": "data/industry_study/industry_dimension_profile_manifest.json"
    },
    "heatmap_registry": {
      "path": "data/industry_study/industry_heatmap_registry.csv",
      "exists": true,
      "bytes": 2984,
      "sha256": "7e1365c7751adff34a6acd2192129652163403e8f49ff16a84a715bc9dc0c2e1"
    }
  },
  "stages": [
    {
      "id": "load_snapshot_and_catalog",
      "label": "Carregar snapshot e catálogo",
      "status": "ok",
      "input": "data/industry_study/industry_fund_snapshot.csv.gz+data/industry_study/industry_dimension_catalog.csv.gz",
      "output": "memoria:snapshot+dimension_catalog",
      "rows": 78169,
      "rerun": "python scripts/build_fidc_industry_fund_snapshot.py && python scripts/build_fidc_industry_dimensions.py"
    },
    {
      "id": "aggregate_cross_dimension_profiles",
      "label": "Agregar perfis cruzados",
      "status": "ok",
      "input": "memoria:snapshot+dimension_catalog",
      "output": "data/industry_study/industry_dimension_profiles.csv.gz",
      "rows": 92371,
      "profile_links": 1435465,
      "rerun": "python scripts/build_fidc_industry_dimension_profiles.py"
    },
    {
      "id": "register_heatmap_presets",
      "label": "Registrar presets de heatmap",
      "status": "ok",
      "input": "memoria:dimension_profiles+dimension_catalog",
      "output": "data/industry_study/industry_heatmap_registry.csv",
      "rows": 11,
      "available_presets": 11,
      "rerun": "python scripts/build_fidc_industry_dimension_profiles.py"
    }
  ],
  "quality": {
    "rows": 92371,
    "competencia": "2026-05",
    "source_dimensions": 29,
    "target_dimensions": 29,
    "source_values": 1031,
    "target_values": 1031,
    "profile_links": 1435465,
    "with_source_document_links": 495082,
    "curated_links": 60919,
    "weighted_links": 391092,
    "heatmap_preset_rows": 11,
    "heatmap_preset_available": 11,
    "heatmap_preset_profile_available": 11,
    "heatmap_preset_status_counts": {
      "ok": 11
    }
  }
}