{
  "cnpj": "34267684000104",
  "cnpj_raiz": "34267684",
  "razao_social": "SANTA CRUZ CONSULTORIA ESPECIALIZADA LTDA",
  "nome_fantasia": "SANTA CRUZ CAPITAL",
  "cnae_fiscal": "8291100",
  "cnae_descricao": "Atividades de cobranças e informações cadastrais",
  "cnae_secao": "N",
  "setor": "Atividades administrativas e serviços complementares",
  "segmento": "Atividades de cobranças e informações cadastrais",
  "cnaes_secundarios": "",
  "natureza_juridica": "Sociedade Empresária Limitada",
  "porte": "DEMAIS",
  "situacao_cadastral": "2",
  "data_inicio_atividade": "2019-07-19",
  "uf": "SP",
  "municipio": "SAO PAULO",
  "source_provider": "BrasilAPI/CNPJ",
  "source_url": "https://brasilapi.com.br/api/cnpj/v1/34267684000104",
  "fetched_at_utc": "2026-07-10T01:33:59+00:00",
  "registry_status": "ok",
  "error_message": ""
}