{
  "cnpj": "48818746000133",
  "cnpj_raiz": "48818746",
  "razao_social": "ALUMNI INVESTIMENTOS S/A",
  "nome_fantasia": "",
  "cnae_fiscal": "6619302",
  "cnae_descricao": "Correspondentes de instituições financeiras",
  "cnae_secao": "K",
  "setor": "Atividades financeiras, seguros e serviços relacionados",
  "segmento": "Correspondentes de instituições financeiras",
  "cnaes_secundarios": "6462000 - Holdings de instituições não-financeiras | 6492100 - Securitização de créditos | 6499999 - Outras atividades de serviços financeiros não especificadas anteriormente | 6810202 - Aluguel de imóveis próprios | 7020400 - Atividades de consultoria em gestão empresarial, exceto consultoria técnica específica | 7490104 - Atividades de intermediação e agenciamento de serviços e negócios em geral, exceto imobiliários | 8291100 - Atividades de cobranças e informações cadastrais",
  "natureza_juridica": "Sociedade Anônima Fechada",
  "porte": "DEMAIS",
  "situacao_cadastral": "2",
  "data_inicio_atividade": "2022-12-06",
  "uf": "SP",
  "municipio": "RIBEIRAO PRETO",
  "source_provider": "BrasilAPI/CNPJ",
  "source_url": "https://brasilapi.com.br/api/cnpj/v1/48818746000133",
  "fetched_at_utc": "2026-07-10T01:35:16+00:00",
  "registry_status": "ok",
  "error_message": ""
}