{
  "cnpj": "52858530000179",
  "cnpj_raiz": "52858530",
  "razao_social": "SMART COMPASS S.A.",
  "nome_fantasia": "",
  "cnae_fiscal": "8291100",
  "cnae_descricao": "Atividades de cobranças e informações cadastrais",
  "cnae_secao": "N",
  "setor": "Atividades administrativas e serviços complementares",
  "segmento": "Atividades de cobranças e informações cadastrais",
  "cnaes_secundarios": "6462000 - Holdings de instituições não-financeiras | 6821801 - Corretagem na compra e venda e avaliação de imóveis | 6822600 - Gestão e administração da propriedade imobiliária | 7020400 - Atividades de consultoria em gestão empresarial, exceto consultoria técnica específica",
  "natureza_juridica": "Sociedade Anônima Fechada",
  "porte": "DEMAIS",
  "situacao_cadastral": "2",
  "data_inicio_atividade": "2023-11-10",
  "uf": "SP",
  "municipio": "CAMPINAS",
  "source_provider": "BrasilAPI/CNPJ",
  "source_url": "https://brasilapi.com.br/api/cnpj/v1/52858530000179",
  "fetched_at_utc": "2026-07-10T01:34:01+00:00",
  "registry_status": "ok",
  "error_message": ""
}